dave_timeline/__init__.cp312-win_amd64.pyd
dave_timeline/mixins.cp312-win_amd64.pyd
dave_timeline/run_DAVE_with_timeline.cp312-win_amd64.pyd
dave_timeline/solver_worker.cp312-win_amd64.pyd
dave_timeline/stored_results.cp312-win_amd64.pyd
dave_timeline/timeline.cp312-win_amd64.pyd
dave_timeline/gui/__init__.cp312-win_amd64.pyd
dave_timeline/gui/docks/TLdatatablesource.cp312-win_amd64.pyd
dave_timeline/gui/docks/__init__.cp312-win_amd64.pyd
dave_timeline/gui/docks/dock_timeline.cp312-win_amd64.pyd
dave_timeline/gui/forms/__init__.cp312-win_amd64.pyd
dave_timeline/gui/forms/dock_timeline.cp312-win_amd64.pyd
dave_timeline/helpers/__init__.cp312-win_amd64.pyd
dave_timeline/helpers/combinations.cp312-win_amd64.pyd
dave_timeline/helpers/loadcases.cp312-win_amd64.pyd
dave_timeline/helpers/string_helpers.cp312-win_amd64.pyd
dave_timeline/optimizers/__init__.cp312-win_amd64.pyd
dave_timeline/optimizers/solve_limiting_value.cp312-win_amd64.pyd
dave_timeline-2025.0.7.dist-info/licenses/LICENSE.txt
dave_timeline-2025.0.7.dist-info/METADATA
dave_timeline-2025.0.7.dist-info/WHEEL
dave_timeline-2025.0.7.dist-info/entry_points.txt
dave_timeline-2025.0.7.dist-info/top_level.txt
dave_timeline-2025.0.7.dist-info/RECORD
